CheckNoAuth.py
JenkinsEnvHunter.py
jenkinsenvhunter-1.1.1.dist-info/METADATA
jenkinsenvhunter-1.1.1.dist-info/WHEEL
jenkinsenvhunter-1.1.1.dist-info/entry_points.txt
jenkinsenvhunter-1.1.1.dist-info/top_level.txt
jenkinsenvhunter-1.1.1.dist-info/RECORD
