Metadata-Version: 2.4
Name: jenkinsenvhunter
Version: 1.1.1
Summary: Hunts Jenkins jobs and builds for sensitive information in Jenkins environment variables
Author: Defensive Origins
Keywords: jenkins,security,environment-variables,pentest,infosec
Classifier: Development Status :: 4 - Beta
Classifier: Intended Audience :: Information Technology
Classifier: Intended Audience :: System Administrators
Classifier: Topic :: Security
Classifier: Topic :: Software Development :: Testing
Classifier: Programming Language :: Python :: 3
Classifier: Programming Language :: Python :: 3.7
Classifier: Programming Language :: Python :: 3.8
Classifier: Programming Language :: Python :: 3.9
Classifier: Programming Language :: Python :: 3.10
Classifier: Programming Language :: Python :: 3.11
Requires-Python: >=3.7
Requires-Dist: requests
Requires-Dist: alive-progress
